cronman/__init__.py
cronman/admin.py
cronman/apps.py
cronman/base.py
cronman/config.py
cronman/exceptions.py
cronman/forms.py
cronman/job.py
cronman/models.py
cronman/monitor.py
cronman/redis_client.py
cronman/remote_manager.py
cronman/spawner.py
cronman/taxonomies.py
cronman/utils.py
cronman/version.py
cronman/cron_jobs/__init__.py
cronman/cron_jobs/clean_cron_tasks.py
cronman/cron_jobs/run_cron_tasks.py
cronman/cron_jobs/sleep.py
cronman/management/__init__.py
cronman/management/commands/__init__.py
cronman/management/commands/cron_remote_manager.py
cronman/management/commands/cron_scheduler.py
cronman/management/commands/cron_worker.py
cronman/migrations/0001_initial.py
cronman/migrations/__init__.py
cronman/scheduler/__init__.py
cronman/scheduler/files.py
cronman/scheduler/scheduler.py
cronman/tests/__init__.py
cronman/tests/base.py
cronman/tests/cron_jobs.py
cronman/tests/cron_jobs_failing.py
cronman/tests/settings.py
cronman/tests/test_commands.py
cronman/tests/test_cron_jobs.py
cronman/tests/test_forms.py
cronman/tests/test_models.py
cronman/tests/test_monitor.py
cronman/tests/test_scheduler.py
cronman/tests/test_signal_notifier.py
cronman/tests/test_spawner.py
cronman/tests/test_utils.py
cronman/tests/test_worker.py
cronman/tests/tools.py
cronman/worker/__init__.py
cronman/worker/cron_job_info.py
cronman/worker/process_manager.py
cronman/worker/signal_notifier.py
cronman/worker/worker.py
cronman/worker/worker_file.py
cronman/worker/worker_list.py
django_cronman-1.2.0.dist-info/LICENCE.txt
django_cronman-1.2.0.dist-info/METADATA
django_cronman-1.2.0.dist-info/WHEEL
django_cronman-1.2.0.dist-info/pbr.json
django_cronman-1.2.0.dist-info/top_level.txt
django_cronman-1.2.0.dist-info/RECORD
