Metadata-Version: 2.1
Name: django-cronman
Version: 1.2.0
Summary: Cron management app for Django
Home-page: https://github.com/unhaggle/django-cronman
Author: Unhaggle Inc.
Author-email: 
License: UNKNOWN
Platform: UNKNOWN
Classifier: Programming Language :: Python :: 3.6
Classifier: Programming Language :: Python :: 2.7
Classifier: License :: OSI Approved :: BSD License
Classifier: Framework :: Django
Classifier: Framework :: Django :: 1.11
Classifier: Environment :: Web Environment
Classifier: Operating System :: POSIX
Classifier: Topic :: Utilities
Requires-Dist: croniter (<0.4)
Requires-Dist: django (<3.0)
Requires-Dist: python-dateutil
Requires-Dist: requests
Requires-Dist: typing
Provides-Extra: redis
Requires-Dist: redis (<2.11) ; extra == 'redis'
Provides-Extra: sentry
Requires-Dist: raven (<5.33) ; extra == 'sentry'
